sorting_ms/__init__.py
sorting_ms/bubble_sort.py
sorting_ms/insertion_sort.py
sorting_ms/quick_sort.py
sorting_ms/selection_sort.py
sorting_ms-0.2.dist-info/METADATA
sorting_ms-0.2.dist-info/WHEEL
sorting_ms-0.2.dist-info/top_level.txt
sorting_ms-0.2.dist-info/RECORD
