Metadata-Version: 2.1
Name: sorting-ms
Version: 0.2
Summary: some simple sorting functions
Home-page: https://gitlab.propulsion-home.ch/marita-salz/week-3/day-4
Author: Marita Salz
Author-email: marita.salz@hispeed.ch
License: MIT
Keywords: sorting function marita salz
Platform: UNKNOWN
Classifier: Development Status :: 3 - Alpha
Classifier: License :: OSI Approved :: MIT License
Classifier: Programming Language :: Python :: 2.7
Classifier: Topic :: Text Processing :: Linguistic
Requires-Dist: markdown
